copilot_api/__init__.py
copilot_api/cli.py
copilot_api/copilot.py
copilot_api/exceptions.py
copilot_api/utils.py
copilot_api-1.0.0.dist-info/LICENSE
copilot_api-1.0.0.dist-info/METADATA
copilot_api-1.0.0.dist-info/WHEEL
copilot_api-1.0.0.dist-info/top_level.txt
copilot_api-1.0.0.dist-info/RECORD
